{
  "title": "Impact of employment on housing prices",
  "name": "Impact of employment on housing prices",
  "description": " The objective is to find and to contribute to the creation of smarter, gain deeper insights into the dynamics of cities, and identify the areas for improvement, and develop innovative solutions to advance inclusive and strong communities.",
  "tags": [
      "Jobs per ANZSIC for blocks",
      "House Prices by Small Area"
  ],
  "difficultly": "Intermediete",
  "technology": [
      {
          "name": "json",
          "code": "python"
      },
      {
          "name": "pandas",
          "code": "python"
      },
      {
          "name": "webbrowser",
          "code": "python"
      },
      {
          "name": "requests",
          "code": "python"
      },
      {
          "name": "pyplot",
          "code": "python"
      },
      {
          "name": "StandardScaler",
          "code": "python"
      }

  ],
  "datasets": [
      "Jobs per ANZSIC for blocks",
      "House Prices by Small Area - Sale Year"
  ]
}
